pyqreg/__init__.pxd
pyqreg/__init__.py
pyqreg/quantreg.py
pyqreg/c/__init__.py
pyqreg/c/blas_lapack.c
pyqreg/c/blas_lapack.cpython-37m-darwin.so
pyqreg/c/blas_lapack.pxd
pyqreg/c/blas_lapack.pyx
pyqreg/c/fit_coefs.c
pyqreg/c/fit_coefs.cpython-37m-darwin.so
pyqreg/c/fit_coefs.pxd
pyqreg/c/fit_coefs.pyx
pyqreg/c/mat_vec_ops.c
pyqreg/c/mat_vec_ops.cpython-37m-darwin.so
pyqreg/c/mat_vec_ops.pxd
pyqreg/c/mat_vec_ops.pyx
pyqreg-0.0b8.dist-info/LICENSE
pyqreg-0.0b8.dist-info/METADATA
pyqreg-0.0b8.dist-info/WHEEL
pyqreg-0.0b8.dist-info/top_level.txt
pyqreg-0.0b8.dist-info/RECORD
